{"abbr":"nd","name":"North Dakota","house":[{"state":"North Dakota","stateAbbr":"nd","district":0,"party":"Republican","name":"Kelly Armstrong","incumbent":true,"campaignUrl":"https://www.armstrongnd.com/","facebookUrl":"https://www.facebook.com/ArmstrongND/","twitterHandle":"@Armstrong_ND","instagramHandle":"@reparmstrongnd","image":"/images/north-dakota-kelly-armstrong.jpg","battleground":false,"woman":false,"bipoc":false,"type":"house","slug":"kelly-armstrong"},{"state":"North Dakota","stateAbbr":"nd","district":0,"party":"Democrat","name":"Zach Raknerud","incumbent":false,"campaignUrl":"https://www.zachfornorthdakota.com","facebookUrl":"https://www.facebook.com/ZachforND/","twitterHandle":"@ZachforND","instagramHandle":"@zachfornd","image":"/images/north-dakota-zach-raknerud.jpg","battleground":false,"woman":false,"bipoc":false,"type":"house","slug":"zach-raknerud"},{"state":"North Dakota","stateAbbr":"nd","district":0,"party":"Independent","name":"Matthew Austin Gullo","incumbent":false,"campaignUrl":"https://ballotpedia.org/Matthew_Austin_Gullo","battleground":false,"woman":false,"bipoc":false,"type":"house","slug":"matthew-austin-gullo"},{"state":"North Dakota","stateAbbr":"nd","district":0,"party":"Other","name":"Steven Peterson","incumbent":false,"campaignUrl":"https://ballotpedia.org/Steven_Peterson_(North_Dakota)","facebookUrl":"https://www.facebook.com/SJPforUSHouse/","battleground":false,"woman":false,"bipoc":false,"type":"house","slug":"steven-peterson"}],"battleground":false,"battlegroundDistricts":[]}
